{
    "status": "draft",
    "showDataPageOnChartIds": [
        703
    ],
    "title": "Share of children who are stunted",
    "googleDocEditLink": "https://docs.google.com/document/d/1iLb4lxAkenu3zZisz9b3vNQWVorSH4lF2m_8sw-N8sE/edit",
    "topicTagsLinks": [
        {
            "title": "Hunger and Undernourishment",
            "url": "https://ourworldindata.org/hunger-and-undernourishment"
        },
        {
            "title": "Child and Infant Mortality",
            "url": "https://ourworldindata.org/child-mortality"
        },
        {
            "title": "Micronutrient Deficiency",
            "url": "https://ourworldindata.org/micronutrient-deficiency"
        },
        {
            "title": "Famines",
            "url": "https://ourworldindata.org/famines"
        }
    ],
    "variantDescription1": "UNICEF/WHO",
    "variantDescription2": "",
    "nameOfSource": "UNICEF, World Health Organization and World Bank",
    "owidProcessingLevel": "<a href>Processed</a> by Our World in Data",
    "dateRange": "1983-2020",
    "lastUpdated": "2022-06-02",
    "nextUpdate": "June 2023",
    "subtitle": "The share of children younger than five years old whose growth is stunted. Stunting is when a child is significantly shorter than the average for their age. Stunted growth is a consequence of poor nutrition and/or repeated infection.",
    "descriptionFromSource": {
        "title": "How does the data provider – the World Bank – describe this metric?"
    },
    "relatedResearch": [
       
    ],
    "relatedData": [
        {
            "type": "Data Explorer",
            "imageUrl": "https://ourworldindata.org/uploads/2022/10/Global-Health-Explorer.png",
            "title": "Global Health Explorer",
            "source": "Data from various sources",
            "url": "https://ourworldindata.org/explorers/global-health?facet=none&country=OWID_WRL~CHN~ZAF~BRA~USA~GBR~IND~RWA&Health+Area=Child+health&Indicator=Childhood+stunting&Metric=Share+of+children&Source=UNICEF%2FWHO",
            "content": "Explore a wide range of metrics on global health and healthcare."
        },
        {
            "title": "Share of the population that is undernourished",
            "url": "https://ourworldindata.org/grapher/prevalence-of-undernourishment",
            "source": "FAO",
            "content": "See data for another common metric of malnutrition – the share of population with a food intake below that needed for an normal healthy, active life."
        },
        {
            "title": "Share of children who are stunted",
            "url": "https://ourworldindata.org/grapher/child-stunting-ihme",
            "source": "IHME",
            "content": "Compare the same indicator from a different source."
        },
        {
            "title": "Number of children who are stunted",
            "url": "https://ourworldindata.org/grapher/number-children-stunted-ihme",
            "source": "IHME"
        },
        {
            "title": "Hidden hunger in pre-school children",
            "url": "https://ourworldindata.org/grapher/global-hidden-hunger-index-in-pre-school-children",
            "source": "Muthayya et al. (2013)"
        }
    ],
    "relatedCharts": {
        "items": [
            {
                "title": "People without clean cooking fuels",
                "slug": "people-without-clean-cooking-fuels-region"
            },
            {
                "title": "Old-age dependency ratio",
                "slug": "age-dependency-ratio-old",
                "variantName": "Historical estimates",
                "isKeyChart": true
            },
            {
                "title": "Value added in the agricultural sector as of GDP vs GDP per capita",
                "slug": "value-added-in-the-agricultural-sector-as-of-gdp-vs-gdp-per-capita",
                "variantName": "World Bank"
            },
            {
                "title": "Number of people employed in agriculture",
                "slug": "number-of-people-employed-in-agriculture"
            }
        ]
    },
    "datasetName": "World Development Indicators (World Bank) – Processed by Our World in Data",
    "sources": [
        {
            "sourceName": "World Bank World Development Indicators",
            "sourceRetrievedOn": "2022-06-02",
            "sourceRetrievedFromUrl": "https://datacatalog.worldbank.org/search/dataset/0037712/World-Development-Indicators",
            "sourceCodeUrl": "https://ourworldindata.org/explorers/co2"
        }
    ]
}
